youtube_assistant/__init__.py
youtube_assistant/main.py
youtube_assistant-2.1.10.dist-info/METADATA
youtube_assistant-2.1.10.dist-info/WHEEL
youtube_assistant-2.1.10.dist-info/entry_points.txt
youtube_assistant-2.1.10.dist-info/top_level.txt
youtube_assistant-2.1.10.dist-info/RECORD
