Metadata-Version: 2.4
Name: youtube-assistant
Version: 2.1.10
Summary: 一个功能强大的模块化工具，可以从YouTube视频中提取音频，转录为文本，生成字幕，翻译字幕，并使用AI生成高质量文章摘要
Home-page: https://github.com/cacity/youtube-assistant
Author: cacity
Author-email: gf7823332@gmail.com
License: MIT
Requires-Python: >=3.7
Requires-Dist: yt-dlp
Requires-Dist: openai-whisper
Requires-Dist: requests
Requires-Dist: python-dotenv
Requires-Dist: torch
Requires-Dist: ffmpeg-python
Requires-Dist: tqdm
Dynamic: author
Dynamic: author-email
Dynamic: description
Dynamic: description-content-type
Dynamic: home-page
Dynamic: license
Dynamic: requires-dist
Dynamic: requires-python
Dynamic: summary
